{
    "name": "northernblood_bunkers:lamps",
    "fallback": "minecraft:empty",
    "elements": [
      {	
        "weight": 20,
        "element": {
          "location": "bunkers:townparts/lamps/lamp_1",
          "processors": "minecraft:empty",
          "projection": "rigid",
          "element_type": "minecraft:single_pool_element"
        }
      },
      {	
        "weight": 20,
        "element": {
          "location": "bunkers:townparts/lamps/lamp_2",
          "processors": "minecraft:empty",
          "projection": "rigid",
          "element_type": "minecraft:single_pool_element"
        }
      },
      {	
        "weight": 20,
        "element": {
          "location": "bunkers:townparts/lamps/lamp_3",
          "processors": "minecraft:empty",
          "projection": "rigid",
          "element_type": "minecraft:single_pool_element"
        }
      }
    ]
}